<?xml version="1.0" encoding="utf-8"?>
<script>
  <set Settings.AttributesMappingVersion="'1.0.0.0'" />
  <set Settings.AttributesMapping="new Dictionary()" />
  <!--<set var="Settings.AttributesMapping['name']">-->
  <!--<attr name="src">name</attr>-->
  <!--<attr name="dst">name</attr>-->
  <!--<attr name="type">string</attr>-->
  <!--</set>-->
  <set var="Settings.AttributesMapping['address2_postalcode']">
    <attr name="src">address2_postalcode</attr>
    <attr name="dst">address2_postalcode</attr>
    <attr name="type">String</attr>
    <attr name="validForCreate">{true}</attr>
    <attr name="validForUpdate">{true}</attr>
    <attr name="required">{false}</attr>
  </set>
  <set var="Settings.AttributesMapping['address2_county']">
    <attr name="src">address2_county</attr>
    <attr name="dst">address2_county</attr>
    <attr name="type">String</attr>
    <attr name="validForCreate">{true}</attr>
    <attr name="validForUpdate">{true}</attr>
    <attr name="required">{false}</attr>
  </set>
  <set var="Settings.AttributesMapping['yomicompanyname']">
    <attr name="src">yomicompanyname</attr>
    <attr name="dst">yomicompanyname</attr>
    <attr name="type">String</attr>
    <attr name="validForCreate">{true}</attr>
    <attr name="validForUpdate">{true}</attr>
    <attr name="required">{false}</attr>
  </set>
  <set var="Settings.AttributesMapping['pager']">
    <attr name="src">pager</attr>
    <attr name="dst">pager</attr>
    <attr name="type">String</attr>
    <attr name="validForCreate">{true}</attr>
    <attr name="validForUpdate">{true}</attr>
    <attr name="required">{false}</attr>
  </set>
  <set var="Settings.AttributesMapping['address1_county']">
    <attr name="src">address1_county</attr>
    <attr name="dst">address1_county</attr>
    <attr name="type">String</attr>
    <attr name="validForCreate">{true}</attr>
    <attr name="validForUpdate">{true}</attr>
    <attr name="required">{false}</attr>
  </set>
  <set var="Settings.AttributesMapping['modifiedby']">
    <attr name="src">modifiedby</attr>
    <attr name="dst">modifiedby</attr>
    <attr name="type">Lookup</attr>
    <attr name="validForCreate">{false}</attr>
    <attr name="validForUpdate">{false}</attr>
    <attr name="required">{false}</attr>
  </set>
  <set var="Settings.AttributesMapping['campaignid']">
    <attr name="src">campaignid</attr>
    <attr name="dst">campaignid</attr>
    <attr name="type">Lookup</attr>
    <attr name="validForCreate">{true}</attr>
    <attr name="validForUpdate">{true}</attr>
    <attr name="required">{false}</attr>
  </set>
  <set var="Settings.AttributesMapping['address2_line3']">
    <attr name="src">address2_line3</attr>
    <attr name="dst">address2_line3</attr>
    <attr name="type">String</attr>
    <attr name="validForCreate">{true}</attr>
    <attr name="validForUpdate">{true}</attr>
    <attr name="required">{false}</attr>
  </set>
  <set var="Settings.AttributesMapping['statuscode']">
    <attr name="src">statuscode</attr>
    <attr name="dst">statuscode</attr>
    <attr name="type">Status</attr>
    <attr name="validForCreate">{true}</attr>
    <attr name="validForUpdate">{true}</attr>
    <attr name="required">{false}</attr>
  </set>
  <set var="Settings.AttributesMapping['address2_longitude']">
    <attr name="src">address2_longitude</attr>
    <attr name="dst">address2_longitude</attr>
    <attr name="type">Double</attr>
    <attr name="validForCreate">{true}</attr>
    <attr name="validForUpdate">{true}</attr>
    <attr name="required">{false}</attr>
  </set>
  <set var="Settings.AttributesMapping['modifiedonbehalfby']">
    <attr name="src">modifiedonbehalfby</attr>
    <attr name="dst">modifiedonbehalfby</attr>
    <attr name="type">Lookup</attr>
    <attr name="validForCreate">{false}</attr>
    <attr name="validForUpdate">{false}</attr>
    <attr name="required">{false}</attr>
  </set>
  <set var="Settings.AttributesMapping['relatedobjectid']">
    <attr name="src">relatedobjectid</attr>
    <attr name="dst">relatedobjectid</attr>
    <attr name="type">Lookup</attr>
    <attr name="validForCreate">{true}</attr>
    <attr name="validForUpdate">{false}</attr>
    <attr name="required">{false}</attr>
  </set>
  <set var="Settings.AttributesMapping['middlename']">
    <attr name="src">middlename</attr>
    <attr name="dst">middlename</attr>
    <attr name="type">String</attr>
    <attr name="validForCreate">{true}</attr>
    <attr name="validForUpdate">{true}</attr>
    <attr name="required">{false}</attr>
  </set>
  <set var="Settings.AttributesMapping['decisionmaker']">
    <attr name="src">decisionmaker</attr>
    <attr name="dst">decisionmaker</attr>
    <attr name="type">Boolean</attr>
    <attr name="validForCreate">{true}</attr>
    <attr name="validForUpdate">{true}</attr>
    <attr name="required">{false}</attr>
  </set>
  <set var="Settings.AttributesMapping['address1_upszone']">
    <attr name="src">address1_upszone</attr>
    <attr name="dst">address1_upszone</attr>
    <attr name="type">String</attr>
    <attr name="validForCreate">{true}</attr>
    <attr name="validForUpdate">{true}</attr>
    <attr name="required">{false}</attr>
  </set>
  <set var="Settings.AttributesMapping['processid']">
    <attr name="src">processid</attr>
    <attr name="dst">processid</attr>
    <attr name="type">Uniqueidentifier</attr>
    <attr name="validForCreate">{true}</attr>
    <attr name="validForUpdate">{true}</attr>
    <attr name="required">{false}</attr>
  </set>
  <set var="Settings.AttributesMapping['confirminterest']">
    <attr name="src">confirminterest</attr>
    <attr name="dst">confirminterest</attr>
    <attr name="type">Boolean</attr>
    <attr name="validForCreate">{true}</attr>
    <attr name="validForUpdate">{true}</attr>
    <attr name="required">{false}</attr>
  </set>
  <set var="Settings.AttributesMapping['leadid']">
    <attr name="src">leadid</attr>
    <attr name="dst">leadid</attr>
    <attr name="type">Uniqueidentifier</attr>
    <attr name="validForCreate">{true}</attr>
    <attr name="validForUpdate">{false}</attr>
    <attr name="required">{true}</attr>
  </set>
  <set var="Settings.AttributesMapping['address1_stateorprovince']">
    <attr name="src">address1_stateorprovince</attr>
    <attr name="dst">address1_stateorprovince</attr>
    <attr name="type">String</attr>
    <attr name="validForCreate">{true}</attr>
    <attr name="validForUpdate">{true}</attr>
    <attr name="required">{false}</attr>
  </set>
  <set var="Settings.AttributesMapping['fullname']">
    <attr name="src">fullname</attr>
    <attr name="dst">fullname</attr>
    <attr name="type">String</attr>
    <attr name="validForCreate">{false}</attr>
    <attr name="validForUpdate">{false}</attr>
    <attr name="required">{false}</attr>
  </set>
  <set var="Settings.AttributesMapping['emailaddress2']">
    <attr name="src">emailaddress2</attr>
    <attr name="dst">emailaddress2</attr>
    <attr name="type">String</attr>
    <attr name="validForCreate">{true}</attr>
    <attr name="validForUpdate">{true}</attr>
    <attr name="required">{false}</attr>
  </set>
  <set var="Settings.AttributesMapping['emailaddress1']">
    <attr name="src">emailaddress1</attr>
    <attr name="dst">emailaddress1</attr>
    <attr name="type">String</attr>
    <attr name="validForCreate">{true}</attr>
    <attr name="validForUpdate">{true}</attr>
    <attr name="required">{false}</attr>
  </set>
  <set var="Settings.AttributesMapping['schedulefollowup_qualify']">
    <attr name="src">schedulefollowup_qualify</attr>
    <attr name="dst">schedulefollowup_qualify</attr>
    <attr name="type">DateTime</attr>
    <attr name="validForCreate">{true}</attr>
    <attr name="validForUpdate">{true}</attr>
    <attr name="required">{false}</attr>
  </set>
  <set var="Settings.AttributesMapping['leadqualitycode']">
    <attr name="src">leadqualitycode</attr>
    <attr name="dst">leadqualitycode</attr>
    <attr name="type">Picklist</attr>
    <attr name="validForCreate">{true}</attr>
    <attr name="validForUpdate">{true}</attr>
    <attr name="required">{false}</attr>
  </set>
  <set var="Settings.AttributesMapping['address2_upszone']">
    <attr name="src">address2_upszone</attr>
    <attr name="dst">address2_upszone</attr>
    <attr name="type">String</attr>
    <attr name="validForCreate">{true}</attr>
    <attr name="validForUpdate">{true}</attr>
    <attr name="required">{false}</attr>
  </set>
  <set var="Settings.AttributesMapping['address1_shippingmethodcode']">
    <attr name="src">address1_shippingmethodcode</attr>
    <attr name="dst">address1_shippingmethodcode</attr>
    <attr name="type">Picklist</attr>
    <attr name="validForCreate">{true}</attr>
    <attr name="validForUpdate">{true}</attr>
    <attr name="required">{false}</attr>
  </set>
  <set var="Settings.AttributesMapping['exchangerate']">
    <attr name="src">exchangerate</attr>
    <attr name="dst">exchangerate</attr>
    <attr name="type">Decimal</attr>
    <attr name="validForCreate">{false}</attr>
    <attr name="validForUpdate">{false}</attr>
    <attr name="required">{false}</attr>
  </set>
  <set var="Settings.AttributesMapping['timezoneruleversionnumber']">
    <attr name="src">timezoneruleversionnumber</attr>
    <attr name="dst">timezoneruleversionnumber</attr>
    <attr name="type">Integer</attr>
    <attr name="validForCreate">{true}</attr>
    <attr name="validForUpdate">{true}</attr>
    <attr name="required">{false}</attr>
  </set>
  <set var="Settings.AttributesMapping['jobtitle']">
    <attr name="src">jobtitle</attr>
    <attr name="dst">jobtitle</attr>
    <attr name="type">String</attr>
    <attr name="validForCreate">{true}</attr>
    <attr name="validForUpdate">{true}</attr>
    <attr name="required">{false}</attr>
  </set>
  <set var="Settings.AttributesMapping['ownerid']">
    <attr name="src">ownerid</attr>
    <attr name="dst">ownerid</attr>
    <attr name="type">Owner</attr>
    <attr name="validForCreate">{true}</attr>
    <attr name="validForUpdate">{true}</attr>
    <attr name="required">{true}</attr>
  </set>
  <set var="Settings.AttributesMapping['customerid']">
    <attr name="src">customerid</attr>
    <attr name="dst">customerid</attr>
    <attr name="type">Customer</attr>
    <attr name="validForCreate">{true}</attr>
    <attr name="validForUpdate">{true}</attr>
    <attr name="required">{false}</attr>
  </set>
  <set var="Settings.AttributesMapping['address1_city']">
    <attr name="src">address1_city</attr>
    <attr name="dst">address1_city</attr>
    <attr name="type">String</attr>
    <attr name="validForCreate">{true}</attr>
    <attr name="validForUpdate">{true}</attr>
    <attr name="required">{false}</attr>
  </set>
  <set var="Settings.AttributesMapping['industrycode']">
    <attr name="src">industrycode</attr>
    <attr name="dst">industrycode</attr>
    <attr name="type">Picklist</attr>
    <attr name="validForCreate">{true}</attr>
    <attr name="validForUpdate">{true}</attr>
    <attr name="required">{false}</attr>
  </set>
  <set var="Settings.AttributesMapping['address1_utcoffset']">
    <attr name="src">address1_utcoffset</attr>
    <attr name="dst">address1_utcoffset</attr>
    <attr name="type">Integer</attr>
    <attr name="validForCreate">{true}</attr>
    <attr name="validForUpdate">{true}</attr>
    <attr name="required">{false}</attr>
  </set>
  <set var="Settings.AttributesMapping['address2_stateorprovince']">
    <attr name="src">address2_stateorprovince</attr>
    <attr name="dst">address2_stateorprovince</attr>
    <attr name="type">String</attr>
    <attr name="validForCreate">{true}</attr>
    <attr name="validForUpdate">{true}</attr>
    <attr name="required">{false}</attr>
  </set>
  <set var="Settings.AttributesMapping['telephone1']">
    <attr name="src">telephone1</attr>
    <attr name="dst">telephone1</attr>
    <attr name="type">String</attr>
    <attr name="validForCreate">{true}</attr>
    <attr name="validForUpdate">{true}</attr>
    <attr name="required">{false}</attr>
  </set>
  <set var="Settings.AttributesMapping['createdby']">
    <attr name="src">createdby</attr>
    <attr name="dst">createdby</attr>
    <attr name="type">Lookup</attr>
    <attr name="validForCreate">{false}</attr>
    <attr name="validForUpdate">{false}</attr>
    <attr name="required">{false}</attr>
  </set>
  <set var="Settings.AttributesMapping['firstname']">
    <attr name="src">firstname</attr>
    <attr name="dst">firstname</attr>
    <attr name="type">String</attr>
    <attr name="validForCreate">{true}</attr>
    <attr name="validForUpdate">{true}</attr>
    <attr name="required">{false}</attr>
  </set>
  <set var="Settings.AttributesMapping['address2_shippingmethodcode']">
    <attr name="src">address2_shippingmethodcode</attr>
    <attr name="dst">address2_shippingmethodcode</attr>
    <attr name="type">Picklist</attr>
    <attr name="validForCreate">{true}</attr>
    <attr name="validForUpdate">{true}</attr>
    <attr name="required">{false}</attr>
  </set>
  <set var="Settings.AttributesMapping['modifiedon']">
    <attr name="src">modifiedon</attr>
    <attr name="dst">modifiedon</attr>
    <attr name="type">DateTime</attr>
    <attr name="validForCreate">{false}</attr>
    <attr name="validForUpdate">{false}</attr>
    <attr name="required">{false}</attr>
  </set>
  <set var="Settings.AttributesMapping['transactioncurrencyid']">
    <attr name="src">transactioncurrencyid</attr>
    <attr name="dst">transactioncurrencyid</attr>
    <attr name="type">Lookup</attr>
    <attr name="validForCreate">{true}</attr>
    <attr name="validForUpdate">{true}</attr>
    <attr name="required">{false}</attr>
  </set>
  <set var="Settings.AttributesMapping['createdon']">
    <attr name="src">createdon</attr>
    <attr name="dst">overriddencreatedon</attr>
    <attr name="type">DateTime</attr>
    <attr name="validForCreate">{true}</attr>
    <attr name="validForUpdate">{false}</attr>
    <attr name="required">{true}</attr>
  </set>
  <set var="Settings.AttributesMapping['initialcommunication']">
    <attr name="src">initialcommunication</attr>
    <attr name="dst">initialcommunication</attr>
    <attr name="type">Picklist</attr>
    <attr name="validForCreate">{true}</attr>
    <attr name="validForUpdate">{true}</attr>
    <attr name="required">{false}</attr>
  </set>
  <set var="Settings.AttributesMapping['yomimiddlename']">
    <attr name="src">yomimiddlename</attr>
    <attr name="dst">yomimiddlename</attr>
    <attr name="type">String</attr>
    <attr name="validForCreate">{true}</attr>
    <attr name="validForUpdate">{true}</attr>
    <attr name="required">{false}</attr>
  </set>
  <set var="Settings.AttributesMapping['preferredcontactmethodcode']">
    <attr name="src">preferredcontactmethodcode</attr>
    <attr name="dst">preferredcontactmethodcode</attr>
    <attr name="type">Picklist</attr>
    <attr name="validForCreate">{true}</attr>
    <attr name="validForUpdate">{true}</attr>
    <attr name="required">{false}</attr>
  </set>
  <set var="Settings.AttributesMapping['subject']">
    <attr name="src">subject</attr>
    <attr name="dst">subject</attr>
    <attr name="type">String</attr>
    <attr name="validForCreate">{true}</attr>
    <attr name="validForUpdate">{true}</attr>
    <attr name="required">{false}</attr>
  </set>
  <set var="Settings.AttributesMapping['accountid']">
    <attr name="src">accountid</attr>
    <attr name="dst">accountid</attr>
    <attr name="type">Lookup</attr>
    <attr name="validForCreate">{false}</attr>
    <attr name="validForUpdate">{false}</attr>
    <attr name="required">{false}</attr>
  </set>
  <set var="Settings.AttributesMapping['leadsourcecode']">
    <attr name="src">leadsourcecode</attr>
    <attr name="dst">leadsourcecode</attr>
    <attr name="type">Picklist</attr>
    <attr name="validForCreate">{true}</attr>
    <attr name="validForUpdate">{true}</attr>
    <attr name="required">{false}</attr>
  </set>
  <set var="Settings.AttributesMapping['schedulefollowup_prospect']">
    <attr name="src">schedulefollowup_prospect</attr>
    <attr name="dst">schedulefollowup_prospect</attr>
    <attr name="type">DateTime</attr>
    <attr name="validForCreate">{true}</attr>
    <attr name="validForUpdate">{true}</attr>
    <attr name="required">{false}</attr>
  </set>
  <set var="Settings.AttributesMapping['address2_addressid']">
    <attr name="src">address2_addressid</attr>
    <attr name="dst">address2_addressid</attr>
    <attr name="type">Uniqueidentifier</attr>
    <attr name="validForCreate">{true}</attr>
    <attr name="validForUpdate">{true}</attr>
    <attr name="required">{false}</attr>
  </set>
  <set var="Settings.AttributesMapping['evaluatefit']">
    <attr name="src">evaluatefit</attr>
    <attr name="dst">evaluatefit</attr>
    <attr name="type">Boolean</attr>
    <attr name="validForCreate">{true}</attr>
    <attr name="validForUpdate">{true}</attr>
    <attr name="required">{false}</attr>
  </set>
  <set var="Settings.AttributesMapping['yomifullname']">
    <attr name="src">yomifullname</attr>
    <attr name="dst">yomifullname</attr>
    <attr name="type">String</attr>
    <attr name="validForCreate">{false}</attr>
    <attr name="validForUpdate">{false}</attr>
    <attr name="required">{false}</attr>
  </set>
  <set var="Settings.AttributesMapping['salutation']">
    <attr name="src">salutation</attr>
    <attr name="dst">salutation</attr>
    <attr name="type">String</attr>
    <attr name="validForCreate">{true}</attr>
    <attr name="validForUpdate">{true}</attr>
    <attr name="required">{false}</attr>
  </set>
  <set var="Settings.AttributesMapping['address2_country']">
    <attr name="src">address2_country</attr>
    <attr name="dst">address2_country</attr>
    <attr name="type">String</attr>
    <attr name="validForCreate">{true}</attr>
    <attr name="validForUpdate">{true}</attr>
    <attr name="required">{false}</attr>
  </set>
  <set var="Settings.AttributesMapping['websiteurl']">
    <attr name="src">websiteurl</attr>
    <attr name="dst">websiteurl</attr>
    <attr name="type">String</attr>
    <attr name="validForCreate">{true}</attr>
    <attr name="validForUpdate">{true}</attr>
    <attr name="required">{false}</attr>
  </set>
  <set var="Settings.AttributesMapping['owninguser']">
    <attr name="src">owninguser</attr>
    <attr name="dst">owninguser</attr>
    <attr name="type">Lookup</attr>
    <attr name="validForCreate">{false}</attr>
    <attr name="validForUpdate">{false}</attr>
    <attr name="required">{false}</attr>
  </set>
  <set var="Settings.AttributesMapping['address2_line2']">
    <attr name="src">address2_line2</attr>
    <attr name="dst">address2_line2</attr>
    <attr name="type">String</attr>
    <attr name="validForCreate">{true}</attr>
    <attr name="validForUpdate">{true}</attr>
    <attr name="required">{false}</attr>
  </set>
  <set var="Settings.AttributesMapping['purchaseprocess']">
    <attr name="src">purchaseprocess</attr>
    <attr name="dst">purchaseprocess</attr>
    <attr name="type">Picklist</attr>
    <attr name="validForCreate">{true}</attr>
    <attr name="validForUpdate">{true}</attr>
    <attr name="required">{false}</attr>
  </set>
  <set var="Settings.AttributesMapping['revenue']">
    <attr name="src">revenue</attr>
    <attr name="dst">revenue</attr>
    <attr name="type">Money</attr>
    <attr name="validForCreate">{true}</attr>
    <attr name="validForUpdate">{true}</attr>
    <attr name="required">{false}</attr>
  </set>
  <set var="Settings.AttributesMapping['address2_fax']">
    <attr name="src">address2_fax</attr>
    <attr name="dst">address2_fax</attr>
    <attr name="type">String</attr>
    <attr name="validForCreate">{true}</attr>
    <attr name="validForUpdate">{true}</attr>
    <attr name="required">{false}</attr>
  </set>
  <set var="Settings.AttributesMapping['address1_latitude']">
    <attr name="src">address1_latitude</attr>
    <attr name="dst">address1_latitude</attr>
    <attr name="type">Double</attr>
    <attr name="validForCreate">{true}</attr>
    <attr name="validForUpdate">{true}</attr>
    <attr name="required">{false}</attr>
  </set>
  <set var="Settings.AttributesMapping['need']">
    <attr name="src">need</attr>
    <attr name="dst">need</attr>
    <attr name="type">Picklist</attr>
    <attr name="validForCreate">{true}</attr>
    <attr name="validForUpdate">{true}</attr>
    <attr name="required">{false}</attr>
  </set>
  <set var="Settings.AttributesMapping['slainvokedid']">
    <attr name="src">slainvokedid</attr>
    <attr name="dst">slainvokedid</attr>
    <attr name="type">Lookup</attr>
    <attr name="validForCreate">{false}</attr>
    <attr name="validForUpdate">{false}</attr>
    <attr name="required">{false}</attr>
  </set>
  <set var="Settings.AttributesMapping['fax']">
    <attr name="src">fax</attr>
    <attr name="dst">fax</attr>
    <attr name="type">String</attr>
    <attr name="validForCreate">{true}</attr>
    <attr name="validForUpdate">{true}</attr>
    <attr name="required">{false}</attr>
  </set>
  <set var="Settings.AttributesMapping['address2_composite']">
    <attr name="src">address2_composite</attr>
    <attr name="dst">address2_composite</attr>
    <attr name="type">Memo</attr>
    <attr name="validForCreate">{false}</attr>
    <attr name="validForUpdate">{false}</attr>
    <attr name="required">{false}</attr>
  </set>
  <set var="Settings.AttributesMapping['address1_name']">
    <attr name="src">address1_name</attr>
    <attr name="dst">address1_name</attr>
    <attr name="type">String</attr>
    <attr name="validForCreate">{true}</attr>
    <attr name="validForUpdate">{true}</attr>
    <attr name="required">{false}</attr>
  </set>
  <set var="Settings.AttributesMapping['purchasetimeframe']">
    <attr name="src">purchasetimeframe</attr>
    <attr name="dst">purchasetimeframe</attr>
    <attr name="type">Picklist</attr>
    <attr name="validForCreate">{true}</attr>
    <attr name="validForUpdate">{true}</attr>
    <attr name="required">{false}</attr>
  </set>
  <set var="Settings.AttributesMapping['salesstage']">
    <attr name="src">salesstage</attr>
    <attr name="dst">salesstage</attr>
    <attr name="type">Picklist</attr>
    <attr name="validForCreate">{true}</attr>
    <attr name="validForUpdate">{true}</attr>
    <attr name="required">{false}</attr>
  </set>
  <set var="Settings.AttributesMapping['qualificationcomments']">
    <attr name="src">qualificationcomments</attr>
    <attr name="dst">qualificationcomments</attr>
    <attr name="type">Memo</attr>
    <attr name="validForCreate">{true}</attr>
    <attr name="validForUpdate">{true}</attr>
    <attr name="required">{false}</attr>
  </set>
  <set var="Settings.AttributesMapping['mobilephone']">
    <attr name="src">mobilephone</attr>
    <attr name="dst">mobilephone</attr>
    <attr name="type">String</attr>
    <attr name="validForCreate">{true}</attr>
    <attr name="validForUpdate">{true}</attr>
    <attr name="required">{false}</attr>
  </set>
  <set var="Settings.AttributesMapping['donotbulkemail']">
    <attr name="src">donotbulkemail</attr>
    <attr name="dst">donotbulkemail</attr>
    <attr name="type">Boolean</attr>
    <attr name="validForCreate">{true}</attr>
    <attr name="validForUpdate">{true}</attr>
    <attr name="required">{false}</attr>
  </set>
  <set var="Settings.AttributesMapping['address2_name']">
    <attr name="src">address2_name</attr>
    <attr name="dst">address2_name</attr>
    <attr name="type">String</attr>
    <attr name="validForCreate">{true}</attr>
    <attr name="validForUpdate">{true}</attr>
    <attr name="required">{false}</attr>
  </set>
  <set var="Settings.AttributesMapping['emailaddress3']">
    <attr name="src">emailaddress3</attr>
    <attr name="dst">emailaddress3</attr>
    <attr name="type">String</attr>
    <attr name="validForCreate">{true}</attr>
    <attr name="validForUpdate">{true}</attr>
    <attr name="required">{false}</attr>
  </set>
  <set var="Settings.AttributesMapping['createdonbehalfby']">
    <attr name="src">createdonbehalfby</attr>
    <attr name="dst">createdonbehalfby</attr>
    <attr name="type">Lookup</attr>
    <attr name="validForCreate">{false}</attr>
    <attr name="validForUpdate">{false}</attr>
    <attr name="required">{false}</attr>
  </set>
  <set var="Settings.AttributesMapping['budgetstatus']">
    <attr name="src">budgetstatus</attr>
    <attr name="dst">budgetstatus</attr>
    <attr name="type">Picklist</attr>
    <attr name="validForCreate">{true}</attr>
    <attr name="validForUpdate">{true}</attr>
    <attr name="required">{false}</attr>
  </set>
  <set var="Settings.AttributesMapping['teamsfollowed']">
    <attr name="src">teamsfollowed</attr>
    <attr name="dst">teamsfollowed</attr>
    <attr name="type">Integer</attr>
    <attr name="validForCreate">{true}</attr>
    <attr name="validForUpdate">{true}</attr>
    <attr name="required">{false}</attr>
  </set>
  <set var="Settings.AttributesMapping['budgetamount_base']">
    <attr name="src">budgetamount_base</attr>
    <attr name="dst">budgetamount_base</attr>
    <attr name="type">Money</attr>
    <attr name="validForCreate">{false}</attr>
    <attr name="validForUpdate">{false}</attr>
    <attr name="required">{false}</attr>
  </set>
  <set var="Settings.AttributesMapping['donotpostalmail']">
    <attr name="src">donotpostalmail</attr>
    <attr name="dst">donotpostalmail</attr>
    <attr name="type">Boolean</attr>
    <attr name="validForCreate">{true}</attr>
    <attr name="validForUpdate">{true}</attr>
    <attr name="required">{false}</attr>
  </set>
  <set var="Settings.AttributesMapping['versionnumber']">
    <attr name="src">versionnumber</attr>
    <attr name="dst">versionnumber</attr>
    <attr name="type">BigInt</attr>
    <attr name="validForCreate">{false}</attr>
    <attr name="validForUpdate">{false}</attr>
    <attr name="required">{false}</attr>
  </set>
  <set var="Settings.AttributesMapping['address1_country']">
    <attr name="src">address1_country</attr>
    <attr name="dst">address1_country</attr>
    <attr name="type">String</attr>
    <attr name="validForCreate">{true}</attr>
    <attr name="validForUpdate">{true}</attr>
    <attr name="required">{false}</attr>
  </set>
  <set var="Settings.AttributesMapping['telephone2']">
    <attr name="src">telephone2</attr>
    <attr name="dst">telephone2</attr>
    <attr name="type">String</attr>
    <attr name="validForCreate">{true}</attr>
    <attr name="validForUpdate">{true}</attr>
    <attr name="required">{false}</attr>
  </set>
  <set var="Settings.AttributesMapping['lastusedincampaign']">
    <attr name="src">lastusedincampaign</attr>
    <attr name="dst">lastusedincampaign</attr>
    <attr name="type">DateTime</attr>
    <attr name="validForCreate">{false}</attr>
    <attr name="validForUpdate">{true}</attr>
    <attr name="required">{false}</attr>
  </set>
  <set var="Settings.AttributesMapping['address1_line3']">
    <attr name="src">address1_line3</attr>
    <attr name="dst">address1_line3</attr>
    <attr name="type">String</attr>
    <attr name="validForCreate">{true}</attr>
    <attr name="validForUpdate">{true}</attr>
    <attr name="required">{false}</attr>
  </set>
  <set var="Settings.AttributesMapping['masterid']">
    <attr name="src">masterid</attr>
    <attr name="dst">masterid</attr>
    <attr name="type">Lookup</attr>
    <attr name="validForCreate">{false}</attr>
    <attr name="validForUpdate">{false}</attr>
    <attr name="required">{false}</attr>
  </set>
  <set var="Settings.AttributesMapping['yomifirstname']">
    <attr name="src">yomifirstname</attr>
    <attr name="dst">yomifirstname</attr>
    <attr name="type">String</attr>
    <attr name="validForCreate">{true}</attr>
    <attr name="validForUpdate">{true}</attr>
    <attr name="required">{false}</attr>
  </set>
  <set var="Settings.AttributesMapping['lastname']">
    <attr name="src">lastname</attr>
    <attr name="dst">lastname</attr>
    <attr name="type">String</attr>
    <attr name="validForCreate">{true}</attr>
    <attr name="validForUpdate">{true}</attr>
    <attr name="required">{false}</attr>
  </set>
  <set var="Settings.AttributesMapping['timespentbymeonemailandmeetings']">
    <attr name="src">timespentbymeonemailandmeetings</attr>
    <attr name="dst">timespentbymeonemailandmeetings</attr>
    <attr name="type">String</attr>
    <attr name="validForCreate">{false}</attr>
    <attr name="validForUpdate">{false}</attr>
    <attr name="required">{false}</attr>
  </set>
  <set var="Settings.AttributesMapping['donotphone']">
    <attr name="src">donotphone</attr>
    <attr name="dst">donotphone</attr>
    <attr name="type">Boolean</attr>
    <attr name="validForCreate">{true}</attr>
    <attr name="validForUpdate">{true}</attr>
    <attr name="required">{false}</attr>
  </set>
  <set var="Settings.AttributesMapping['estimatedamount']">
    <attr name="src">estimatedamount</attr>
    <attr name="dst">estimatedamount</attr>
    <attr name="type">Money</attr>
    <attr name="validForCreate">{true}</attr>
    <attr name="validForUpdate">{true}</attr>
    <attr name="required">{false}</attr>
  </set>
  <set var="Settings.AttributesMapping['estimatedclosedate']">
    <attr name="src">estimatedclosedate</attr>
    <attr name="dst">estimatedclosedate</attr>
    <attr name="type">DateTime</attr>
    <attr name="validForCreate">{true}</attr>
    <attr name="validForUpdate">{true}</attr>
    <attr name="required">{false}</attr>
  </set>
  <set var="Settings.AttributesMapping['address2_postofficebox']">
    <attr name="src">address2_postofficebox</attr>
    <attr name="dst">address2_postofficebox</attr>
    <attr name="type">String</attr>
    <attr name="validForCreate">{true}</attr>
    <attr name="validForUpdate">{true}</attr>
    <attr name="required">{false}</attr>
  </set>
  <set var="Settings.AttributesMapping['prioritycode']">
    <attr name="src">prioritycode</attr>
    <attr name="dst">prioritycode</attr>
    <attr name="type">Picklist</attr>
    <attr name="validForCreate">{true}</attr>
    <attr name="validForUpdate">{true}</attr>
    <attr name="required">{false}</attr>
  </set>
  <set var="Settings.AttributesMapping['donotsendmm']">
    <attr name="src">donotsendmm</attr>
    <attr name="dst">donotsendmm</attr>
    <attr name="type">Boolean</attr>
    <attr name="validForCreate">{true}</attr>
    <attr name="validForUpdate">{true}</attr>
    <attr name="required">{false}</attr>
  </set>
  <set var="Settings.AttributesMapping['parentaccountid']">
    <attr name="src">parentaccountid</attr>
    <attr name="dst">parentaccountid</attr>
    <attr name="type">Lookup</attr>
    <attr name="validForCreate">{true}</attr>
    <attr name="validForUpdate">{true}</attr>
    <attr name="required">{false}</attr>
  </set>
  <set var="Settings.AttributesMapping['slaid']">
    <attr name="src">slaid</attr>
    <attr name="dst">slaid</attr>
    <attr name="type">Lookup</attr>
    <attr name="validForCreate">{true}</attr>
    <attr name="validForUpdate">{true}</attr>
    <attr name="required">{false}</attr>
  </set>
  <set var="Settings.AttributesMapping['address1_composite']">
    <attr name="src">address1_composite</attr>
    <attr name="dst">address1_composite</attr>
    <attr name="type">Memo</attr>
    <attr name="validForCreate">{false}</attr>
    <attr name="validForUpdate">{false}</attr>
    <attr name="required">{false}</attr>
  </set>
  <set var="Settings.AttributesMapping['qualifyingopportunityid']">
    <attr name="src">qualifyingopportunityid</attr>
    <attr name="dst">qualifyingopportunityid</attr>
    <attr name="type">Lookup</attr>
    <attr name="validForCreate">{true}</attr>
    <attr name="validForUpdate">{true}</attr>
    <attr name="required">{false}</attr>
  </set>
  <set var="Settings.AttributesMapping['yomilastname']">
    <attr name="src">yomilastname</attr>
    <attr name="dst">yomilastname</attr>
    <attr name="type">String</attr>
    <attr name="validForCreate">{true}</attr>
    <attr name="validForUpdate">{true}</attr>
    <attr name="required">{false}</attr>
  </set>
  <set var="Settings.AttributesMapping['sic']">
    <attr name="src">sic</attr>
    <attr name="dst">sic</attr>
    <attr name="type">String</attr>
    <attr name="validForCreate">{true}</attr>
    <attr name="validForUpdate">{true}</attr>
    <attr name="required">{false}</attr>
  </set>
  <set var="Settings.AttributesMapping['address2_line1']">
    <attr name="src">address2_line1</attr>
    <attr name="dst">address2_line1</attr>
    <attr name="type">String</attr>
    <attr name="validForCreate">{true}</attr>
    <attr name="validForUpdate">{true}</attr>
    <attr name="required">{false}</attr>
  </set>
  <set var="Settings.AttributesMapping['parentcontactid']">
    <attr name="src">parentcontactid</attr>
    <attr name="dst">parentcontactid</attr>
    <attr name="type">Lookup</attr>
    <attr name="validForCreate">{true}</attr>
    <attr name="validForUpdate">{true}</attr>
    <attr name="required">{false}</attr>
  </set>
  <set var="Settings.AttributesMapping['owningbusinessunit']">
    <attr name="src">owningbusinessunit</attr>
    <attr name="dst">owningbusinessunit</attr>
    <attr name="type">Lookup</attr>
    <attr name="validForCreate">{false}</attr>
    <attr name="validForUpdate">{false}</attr>
    <attr name="required">{false}</attr>
  </set>
  <set var="Settings.AttributesMapping['lastonholdtime']">
    <attr name="src">lastonholdtime</attr>
    <attr name="dst">lastonholdtime</attr>
    <attr name="type">DateTime</attr>
    <attr name="validForCreate">{true}</attr>
    <attr name="validForUpdate">{true}</attr>
    <attr name="required">{false}</attr>
  </set>
  <set var="Settings.AttributesMapping['salesstagecode']">
    <attr name="src">salesstagecode</attr>
    <attr name="dst">salesstagecode</attr>
    <attr name="type">Picklist</attr>
    <attr name="validForCreate">{true}</attr>
    <attr name="validForUpdate">{true}</attr>
    <attr name="required">{false}</attr>
  </set>
  <set var="Settings.AttributesMapping['estimatedvalue']">
    <attr name="src">estimatedvalue</attr>
    <attr name="dst">estimatedvalue</attr>
    <attr name="type">Double</attr>
    <attr name="validForCreate">{true}</attr>
    <attr name="validForUpdate">{true}</attr>
    <attr name="required">{false}</attr>
  </set>
  <set var="Settings.AttributesMapping['address1_telephone1']">
    <attr name="src">address1_telephone1</attr>
    <attr name="dst">address1_telephone1</attr>
    <attr name="type">String</attr>
    <attr name="validForCreate">{true}</attr>
    <attr name="validForUpdate">{true}</attr>
    <attr name="required">{false}</attr>
  </set>
  <set var="Settings.AttributesMapping['address1_telephone2']">
    <attr name="src">address1_telephone2</attr>
    <attr name="dst">address1_telephone2</attr>
    <attr name="type">String</attr>
    <attr name="validForCreate">{true}</attr>
    <attr name="validForUpdate">{true}</attr>
    <attr name="required">{false}</attr>
  </set>
  <set var="Settings.AttributesMapping['address1_telephone3']">
    <attr name="src">address1_telephone3</attr>
    <attr name="dst">address1_telephone3</attr>
    <attr name="type">String</attr>
    <attr name="validForCreate">{true}</attr>
    <attr name="validForUpdate">{true}</attr>
    <attr name="required">{false}</attr>
  </set>
  <set var="Settings.AttributesMapping['description']">
    <attr name="src">description</attr>
    <attr name="dst">description</attr>
    <attr name="type">Memo</attr>
    <attr name="validForCreate">{true}</attr>
    <attr name="validForUpdate">{true}</attr>
    <attr name="required">{false}</attr>
  </set>
  <set var="Settings.AttributesMapping['stageid']">
    <attr name="src">stageid</attr>
    <attr name="dst">stageid</attr>
    <attr name="type">Uniqueidentifier</attr>
    <attr name="validForCreate">{true}</attr>
    <attr name="validForUpdate">{true}</attr>
    <attr name="required">{false}</attr>
  </set>
  <set var="Settings.AttributesMapping['budgetamount']">
    <attr name="src">budgetamount</attr>
    <attr name="dst">budgetamount</attr>
    <attr name="type">Money</attr>
    <attr name="validForCreate">{true}</attr>
    <attr name="validForUpdate">{true}</attr>
    <attr name="required">{false}</attr>
  </set>
  <set var="Settings.AttributesMapping['address2_addresstypecode']">
    <attr name="src">address2_addresstypecode</attr>
    <attr name="dst">address2_addresstypecode</attr>
    <attr name="type">Picklist</attr>
    <attr name="validForCreate">{true}</attr>
    <attr name="validForUpdate">{true}</attr>
    <attr name="required">{false}</attr>
  </set>
  <set var="Settings.AttributesMapping['address1_longitude']">
    <attr name="src">address1_longitude</attr>
    <attr name="dst">address1_longitude</attr>
    <attr name="type">Double</attr>
    <attr name="validForCreate">{true}</attr>
    <attr name="validForUpdate">{true}</attr>
    <attr name="required">{false}</attr>
  </set>
  <set var="Settings.AttributesMapping['utcconversiontimezonecode']">
    <attr name="src">utcconversiontimezonecode</attr>
    <attr name="dst">utcconversiontimezonecode</attr>
    <attr name="type">Integer</attr>
    <attr name="validForCreate">{true}</attr>
    <attr name="validForUpdate">{true}</attr>
    <attr name="required">{false}</attr>
  </set>
  <set var="Settings.AttributesMapping['contactid']">
    <attr name="src">contactid</attr>
    <attr name="dst">contactid</attr>
    <attr name="type">Lookup</attr>
    <attr name="validForCreate">{false}</attr>
    <attr name="validForUpdate">{false}</attr>
    <attr name="required">{false}</attr>
  </set>
  <set var="Settings.AttributesMapping['address1_addressid']">
    <attr name="src">address1_addressid</attr>
    <attr name="dst">address1_addressid</attr>
    <attr name="type">Uniqueidentifier</attr>
    <attr name="validForCreate">{true}</attr>
    <attr name="validForUpdate">{true}</attr>
    <attr name="required">{false}</attr>
  </set>
  <set var="Settings.AttributesMapping['businesscardattributes']">
    <attr name="src">businesscardattributes</attr>
    <attr name="dst">businesscardattributes</attr>
    <attr name="type">String</attr>
    <attr name="validForCreate">{true}</attr>
    <attr name="validForUpdate">{true}</attr>
    <attr name="required">{false}</attr>
  </set>
  <set var="Settings.AttributesMapping['address2_utcoffset']">
    <attr name="src">address2_utcoffset</attr>
    <attr name="dst">address2_utcoffset</attr>
    <attr name="type">Integer</attr>
    <attr name="validForCreate">{true}</attr>
    <attr name="validForUpdate">{true}</attr>
    <attr name="required">{false}</attr>
  </set>
  <set var="Settings.AttributesMapping['estimatedamount_base']">
    <attr name="src">estimatedamount_base</attr>
    <attr name="dst">estimatedamount_base</attr>
    <attr name="type">Money</attr>
    <attr name="validForCreate">{false}</attr>
    <attr name="validForUpdate">{false}</attr>
    <attr name="required">{false}</attr>
  </set>
  <set var="Settings.AttributesMapping['statecode']">
    <attr name="src">statecode</attr>
    <attr name="dst">statecode</attr>
    <attr name="type">State</attr>
    <attr name="validForCreate">{false}</attr>
    <attr name="validForUpdate">{true}</attr>
    <attr name="required">{true}</attr>
  </set>
  <set var="Settings.AttributesMapping['owningteam']">
    <attr name="src">owningteam</attr>
    <attr name="dst">owningteam</attr>
    <attr name="type">Lookup</attr>
    <attr name="validForCreate">{false}</attr>
    <attr name="validForUpdate">{false}</attr>
    <attr name="required">{false}</attr>
  </set>
  <set var="Settings.AttributesMapping['address2_city']">
    <attr name="src">address2_city</attr>
    <attr name="dst">address2_city</attr>
    <attr name="type">String</attr>
    <attr name="validForCreate">{true}</attr>
    <attr name="validForUpdate">{true}</attr>
    <attr name="required">{false}</attr>
  </set>
  <set var="Settings.AttributesMapping['msdyn_gdproptout']">
    <attr name="src">msdyn_gdproptout</attr>
    <attr name="dst">msdyn_gdproptout</attr>
    <attr name="type">Boolean</attr>
    <attr name="validForCreate">{true}</attr>
    <attr name="validForUpdate">{true}</attr>
    <attr name="required">{false}</attr>
  </set>
  <set var="Settings.AttributesMapping['address2_latitude']">
    <attr name="src">address2_latitude</attr>
    <attr name="dst">address2_latitude</attr>
    <attr name="type">Double</attr>
    <attr name="validForCreate">{true}</attr>
    <attr name="validForUpdate">{true}</attr>
    <attr name="required">{false}</attr>
  </set>
  <set var="Settings.AttributesMapping['merged']">
    <attr name="src">merged</attr>
    <attr name="dst">merged</attr>
    <attr name="type">Boolean</attr>
    <attr name="validForCreate">{false}</attr>
    <attr name="validForUpdate">{false}</attr>
    <attr name="required">{false}</attr>
  </set>
  <set var="Settings.AttributesMapping['traversedpath']">
    <attr name="src">traversedpath</attr>
    <attr name="dst">traversedpath</attr>
    <attr name="type">String</attr>
    <attr name="validForCreate">{true}</attr>
    <attr name="validForUpdate">{true}</attr>
    <attr name="required">{false}</attr>
  </set>
  <set var="Settings.AttributesMapping['onholdtime']">
    <attr name="src">onholdtime</attr>
    <attr name="dst">onholdtime</attr>
    <attr name="type">Integer</attr>
    <attr name="validForCreate">{false}</attr>
    <attr name="validForUpdate">{false}</attr>
    <attr name="required">{false}</attr>
  </set>
  <set var="Settings.AttributesMapping['address1_line1']">
    <attr name="src">address1_line1</attr>
    <attr name="dst">address1_line1</attr>
    <attr name="type">String</attr>
    <attr name="validForCreate">{true}</attr>
    <attr name="validForUpdate">{true}</attr>
    <attr name="required">{false}</attr>
  </set>
  <set var="Settings.AttributesMapping['address1_postofficebox']">
    <attr name="src">address1_postofficebox</attr>
    <attr name="dst">address1_postofficebox</attr>
    <attr name="type">String</attr>
    <attr name="validForCreate">{true}</attr>
    <attr name="validForUpdate">{true}</attr>
    <attr name="required">{false}</attr>
  </set>
  <set var="Settings.AttributesMapping['entityimageid']">
    <attr name="src">entityimageid</attr>
    <attr name="dst">entityimageid</attr>
    <attr name="type">Uniqueidentifier</attr>
    <attr name="validForCreate">{false}</attr>
    <attr name="validForUpdate">{false}</attr>
    <attr name="required">{false}</attr>
  </set>
  <set var="Settings.AttributesMapping['originatingcaseid']">
    <attr name="src">originatingcaseid</attr>
    <attr name="dst">originatingcaseid</attr>
    <attr name="type">Lookup</attr>
    <attr name="validForCreate">{true}</attr>
    <attr name="validForUpdate">{true}</attr>
    <attr name="required">{false}</attr>
  </set>
  <set var="Settings.AttributesMapping['companyname']">
    <attr name="src">companyname</attr>
    <attr name="dst">companyname</attr>
    <attr name="type">String</attr>
    <attr name="validForCreate">{true}</attr>
    <attr name="validForUpdate">{true}</attr>
    <attr name="required">{false}</attr>
  </set>
  <set var="Settings.AttributesMapping['donotfax']">
    <attr name="src">donotfax</attr>
    <attr name="dst">donotfax</attr>
    <attr name="type">Boolean</attr>
    <attr name="validForCreate">{true}</attr>
    <attr name="validForUpdate">{true}</attr>
    <attr name="required">{false}</attr>
  </set>
  <set var="Settings.AttributesMapping['address2_telephone1']">
    <attr name="src">address2_telephone1</attr>
    <attr name="dst">address2_telephone1</attr>
    <attr name="type">String</attr>
    <attr name="validForCreate">{true}</attr>
    <attr name="validForUpdate">{true}</attr>
    <attr name="required">{false}</attr>
  </set>
  <set var="Settings.AttributesMapping['address2_telephone2']">
    <attr name="src">address2_telephone2</attr>
    <attr name="dst">address2_telephone2</attr>
    <attr name="type">String</attr>
    <attr name="validForCreate">{true}</attr>
    <attr name="validForUpdate">{true}</attr>
    <attr name="required">{false}</attr>
  </set>
  <set var="Settings.AttributesMapping['address2_telephone3']">
    <attr name="src">address2_telephone3</attr>
    <attr name="dst">address2_telephone3</attr>
    <attr name="type">String</attr>
    <attr name="validForCreate">{true}</attr>
    <attr name="validForUpdate">{true}</attr>
    <attr name="required">{false}</attr>
  </set>
  <set var="Settings.AttributesMapping['address1_line2']">
    <attr name="src">address1_line2</attr>
    <attr name="dst">address1_line2</attr>
    <attr name="type">String</attr>
    <attr name="validForCreate">{true}</attr>
    <attr name="validForUpdate">{true}</attr>
    <attr name="required">{false}</attr>
  </set>
  <set var="Settings.AttributesMapping['revenue_base']">
    <attr name="src">revenue_base</attr>
    <attr name="dst">revenue_base</attr>
    <attr name="type">Money</attr>
    <attr name="validForCreate">{false}</attr>
    <attr name="validForUpdate">{false}</attr>
    <attr name="required">{false}</attr>
  </set>
  <set var="Settings.AttributesMapping['donotemail']">
    <attr name="src">donotemail</attr>
    <attr name="dst">donotemail</attr>
    <attr name="type">Boolean</attr>
    <attr name="validForCreate">{true}</attr>
    <attr name="validForUpdate">{true}</attr>
    <attr name="required">{false}</attr>
  </set>
  <set var="Settings.AttributesMapping['numberofemployees']">
    <attr name="src">numberofemployees</attr>
    <attr name="dst">numberofemployees</attr>
    <attr name="type">Integer</attr>
    <attr name="validForCreate">{true}</attr>
    <attr name="validForUpdate">{true}</attr>
    <attr name="required">{false}</attr>
  </set>
  <set var="Settings.AttributesMapping['address1_addresstypecode']">
    <attr name="src">address1_addresstypecode</attr>
    <attr name="dst">address1_addresstypecode</attr>
    <attr name="type">Picklist</attr>
    <attr name="validForCreate">{true}</attr>
    <attr name="validForUpdate">{true}</attr>
    <attr name="required">{false}</attr>
  </set>
  <set var="Settings.AttributesMapping['address1_fax']">
    <attr name="src">address1_fax</attr>
    <attr name="dst">address1_fax</attr>
    <attr name="type">String</attr>
    <attr name="validForCreate">{true}</attr>
    <attr name="validForUpdate">{true}</attr>
    <attr name="required">{false}</attr>
  </set>
  <set var="Settings.AttributesMapping['importsequencenumber']">
    <attr name="src">importsequencenumber</attr>
    <attr name="dst">importsequencenumber</attr>
    <attr name="type">Integer</attr>
    <attr name="validForCreate">{true}</attr>
    <attr name="validForUpdate">{false}</attr>
    <attr name="required">{false}</attr>
  </set>
  <set var="Settings.AttributesMapping['followemail']">
    <attr name="src">followemail</attr>
    <attr name="dst">followemail</attr>
    <attr name="type">Boolean</attr>
    <attr name="validForCreate">{true}</attr>
    <attr name="validForUpdate">{true}</attr>
    <attr name="required">{false}</attr>
  </set>
  <set var="Settings.AttributesMapping['participatesinworkflow']">
    <attr name="src">participatesinworkflow</attr>
    <attr name="dst">participatesinworkflow</attr>
    <attr name="type">Boolean</attr>
    <attr name="validForCreate">{true}</attr>
    <attr name="validForUpdate">{true}</attr>
    <attr name="required">{false}</attr>
  </set>
  <set var="Settings.AttributesMapping['businesscard']">
    <attr name="src">businesscard</attr>
    <attr name="dst">businesscard</attr>
    <attr name="type">Memo</attr>
    <attr name="validForCreate">{true}</attr>
    <attr name="validForUpdate">{true}</attr>
    <attr name="required">{false}</attr>
  </set>
  <set var="Settings.AttributesMapping['telephone3']">
    <attr name="src">telephone3</attr>
    <attr name="dst">telephone3</attr>
    <attr name="type">String</attr>
    <attr name="validForCreate">{true}</attr>
    <attr name="validForUpdate">{true}</attr>
    <attr name="required">{false}</attr>
  </set>
  <set var="Settings.AttributesMapping['address1_postalcode']">
    <attr name="src">address1_postalcode</attr>
    <attr name="dst">address1_postalcode</attr>
    <attr name="type">String</attr>
    <attr name="validForCreate">{true}</attr>
    <attr name="validForUpdate">{true}</attr>
    <attr name="required">{false}</attr>
  </set>
</script>